[
  {
    "SKT_LOT":"STK_LOT",
    "account":"U1418343",
    "ticker":"AAPL",
    "name":"APPLE INC",
    "currency":"USD",
    "date":"20150430",
    "time":"10:18:28",
    "amount":100,
    "commission":1,
    "price":126.1,
    "total":1261,
    "commission_eur":0.89204
  },
  {
    "SKT_LOT":"STK_LOT",
    "account":"U1418343",
    "ticker":"BX",
    "name":"BLACKSTONE GROUP LP/THE",
    "currency":"USD",
    "date":"20150723",
    "time":"10:59:53",
    "amount":150,
    "commission":1,
    "price":39.408397,
    "total":591.125958,
    "commission_eur":0.89204
  },
  {
    "SKT_LOT":"STK_LOT",
    "account":"U1418343",
    "ticker":"BX",
    "name":"BLACKSTONE GROUP LP/THE",
    "currency":"USD",
    "date":"20150707",
    "time":"10:08:08",
    "amount":250,
    "commission":1,
    "price":38.424827,
    "total":576.372399,
    "commission_eur":0.89204
  },
  {
    "SKT_LOT":"STK_LOT",
    "account":"U1418343",
    "ticker":"MO",
    "name":"ALTRIA GROUP INC",
    "currency":"USD",
    "date":"20150729",
    "time":"12:12:20",
    "amount":50,
    "commission":1,
    "price":54.45,
    "total":272.25,
    "commission_eur":0.89204
  },
  {
    "SKT_LOT":"STK_LOT",
    "account":"U1418343",
    "ticker":"MO",
    "name":"ALTRIA GROUP INC",
    "currency":"USD",
    "date":"20150518",
    "time":"14:03:40",
    "amount":50,
    "commission":1,
    "price":52.09,
    "total":1302.25,
    "commission_eur":0.89204
  },
  {
    "SKT_LOT":"STK_LOT",
    "account":"U1418343",
    "ticker":"XOM",
    "name":"EXXON MOBIL CORP",
    "currency":"USD",
    "date":"20150629",
    "time":"11:44:09",
    "amount":50,
    "commission":1,
    "price":83.2,
    "total":416,
    "commission_eur":0.89204
  },
  {
    "SKT_LOT":"STK_LOT",
    "account":"U1418343",
    "ticker":"XOM",
    "name":"EXXON MOBIL CORP",
    "currency":"USD",
    "date":"20150527",
    "time":"10:54:38",
    "amount":50,
    "commission":1,
    "price":85.16,
    "total":425.8,
    "commission_eur":0.89204
  }
]
